Workbook

Sheet 02_Historical
A1: Line Item | B1: FY23 | C1: FY24 | D1: FY25
A2: Sponsorship | B2: 189500 | C2: 177800 | D2: 188400
A3: Retail, Merchandising, Apparel & Licensing | B3: 113400 | C3: 125076 | D3: 144874
A4: Total Commercial Revenue | B4: =SUM(B2:B3) -> 302900 | C4: =SUM(C2:C3) -> 302876 | D4: =SUM(D2:D3) -> 333274
A5: Broadcasting Revenue | B5: 209100 | C5: 221745 | D5: 172977
A6: Matchday Revenue | B6: 136400 | C6: 137134 | D6: 160263
A7: Total Revenue | B7: =SUM(B4:B6) -> 648400 | C7: =SUM(C4:C6) -> 661755 | D7: =SUM(D4:D6) -> 666514
A8: Employee Benefit Expenses | B8: -331361 | C8: -364719 | D8: -313256
A9: Other Operating Expenses | B9: -163892 | C9: -149384 | D9: -170429
A10: Depreciation & Impairment | B10: -14401 | C10: -16526 | D10: -17002
A11: Amortisation (Player Registrations) | B11: -170050 | C11: -190123 | D11: -196373
A12: Exceptional Items | B12: 0 | C12: -47778 | D12: -36626
A13: Total Operating Expenses | B13: =SUM(B8:B12) -> -679704 | C13: =SUM(C8:C12) -> -768530 | D13: =SUM(D8:D12) -> -733686
A14: Profit / (Loss) on Disposal of Intangibles | B14: 20442 | C14: 37422 | D14: 48742
A15: Operating Profit / (Loss) [EBIT] | B15: =B7+B13+B14 -> -10862 | C15: =C7+C13+C14 -> -69353 | D15: =D7+D13+D14 -> -18430
A16: Finance Costs | B16: -37869 | C16: -63867 | D16: -58988
A17: Finance Income | B17: 16140 | C17: 2496 | D17: 37754
A18: Net Finance Costs | B18: =B16+B17 -> -21729 | C18: =C16+C17 -> -61371 | D18: =D16+D17 -> -21234
A19: Profit / (Loss) Before Tax | B19: =B15+B18 -> -32591 | C19: =C15+C18 -> -130724 | D19: =D15+D18 -> -39664
A20: Income Tax Credit / (Expense) | B20: 3905 | C20: 17565 | D20: 6641
A21: Net Profit / (Loss) for the Year | B21: =B19+B20 -> -28686 | C21: =C19+C20 -> -113159 | D21: =D19+D20 -> -33023
A23: Line Item | B23: FY23 | C23: FY24 | D23: FY25
A24: Cash Generated from Operations | B24: 128900 | C24: 117500 | D24: 107500
A25: Net Cash Inflow from Operating Activities | B25: 104100 | C25: 85700 | D25: 72700
A26: Tangible CapEx (PPE Payments) | B26: -21600 | C26: -17500 | D26: -44700
A27: Intangible CapEx (Payments for Registrations) | B27: -156200 | C27: -190700 | D27: -278800
A28: Proceeds from Sale of Registrations | B28: 37500 | C28: 37000 | D28: 48800
A29: Net Player Intangible CapEx | B29: =B27+B28 -> -118700 | C29: =C27+C28 -> -153700 | D29: =D27+D28 -> -230000
A30: Cash & Cash Equivalents (Year-End) | B30: 76019 | C30: 73549 | D30: 86105
A31: Senior Secured Notes | B31: -332112 | C31: -334538 | D31: -308914
A32: Secured Term Loan | B32: -175223 | C32: -176509 | D32: -162941
A33: Revolving Credit Facilities (Drawn) | B33: -100000 | C33: -30000 | D33: -160000
A34: Total Gross Financial Debt | B34: =SUM(B31:B33) -> -607335 | C34: =SUM(C31:C33) -> -541047 | D34: =SUM(D31:D33) -> -631855
A35: Net Financial Debt | B35: =B34+B30 -> -531316 | C35: =C34+C30 -> -467498 | D35: =D34+D30 -> -545750
A37: YoY Total Revenue Growth | B37: -% | C37: =(C7-B7)/B7 -> 0.020596854 | D37: =(D7-C7)/C7 -> 0.0071914833
A38: % Commerical Revenue | B38: =B4/B7 -> 0.46714991 | C38: =C4/C7 -> 0.457686 | D38: =D4/D7 -> 0.50002551
A39: % Broadcasting Revenue | B39: =B5/B7 -> 0.32248612 | C39: =C5/C7 -> 0.33508625 | D39: =D5/D7 -> 0.25952493
A40: % Matchday Revenue | B40: =B6/B7 -> 0.21036397 | C40: =C6/C7 -> 0.20722775 | D40: =D6/D7 -> 0.24044956
A41: Wage-to-Revenue Ratio | B41: =IFERROR(-B8/B7, "-") -> 0.51104411 | C41: =IFERROR(-C8/C7, "-") -> 0.55113902 | D41: =IFERROR(-D8/D7, "-") -> 0.46999163
A42: Adjusted EBITDA | B42: =B15-B10-B11-B12-B14 -> 153147 | C42: =C15-C10-C11-C12-C14 -> 147652 | D42: =D15-D10-D11-D12-D14 -> 182829

Sheet 03_Drivers
D3: Metric | E3: FY26 | F3: FY27 | G3: FY28 | H3: FY29 | I3: FY30
D4: Sponsorship Growth (%) | E4: 0.025 | F4: 0.025 | G4: 0.03 | H4: 0.03 | I4: 0.03
D5: Adidas Non-UCL Penalty (£'000s) | E5: -10000 | F5: -10000 | G5: 0 | H5: 0 | I5: 0
D6: Retail/Merch Organic Growth (%) | E6: 0.05 | F6: 0.05 | G6: 0.05 | H6: 0.05 | I6: 0.05
D7: Broadcasting Scenario Target (£'000s) | E7: 145000 | F7: 185000 | G7: 230000 | H7: 235000 | I7: 240000
D8: Matchday Target Scenario (£'000s) | E8: 135000 | F8: 150000 | G8: 165000 | H8: 170000 | I8: 175000
D9: Wage-to-Revenue Ratio Target (%) | E9: 0.5 | F9: 0.48 | G9: 0.47 | H9: 0.46 | I9: 0.45
D10: Other OpEx Margin (% of Rev) | E10: 0.238 | F10: 0.243 | G10: 0.243 | H10: 0.24 | I10: 0.238
D11: Depreciation Target (£'000s) | E11: -16000 | F11: -16500 | G11: -17000 | H11: -17500 | I11: -18000
D12: Player Amortisation Target (£'000s) | E12: -170000 | F12: -175000 | G12: -180000 | H12: -185000 | I12: -190000
D13: Net Intangible CapEx (£'000s) | E13: -140000 | F13: -140000 | G13: -140000 | H13: -140000 | I13: -140000
D14: Tangible CapEx (£'000s) | E14: -20000 | F14: -20000 | G14: -20000 | H14: -20000 | I14: -20000
D15: Net Working Capital Change (£'000s) | E15: -5000 | F15: -5000 | G15: -5000 | H15: -5000 | I15: -5000

Sheet 04_DCF_Model
D3: Line Item | E3: FY26E | F3: FY27E | G3: FY28E | H3: FY29E | I3: FY30E
D4: Sponsorship | E4: =('02_Historical'!D2*(1+'03_Drivers'!E4))+'03_Drivers'!E5 -> 183110 | F4: =(E4-'03_Drivers'!E5)*(1+'03_Drivers'!F4)+'03_Drivers'!F5 -> 187937.75 | G4: =(F4-'03_Drivers'!F5)*(1+'03_Drivers'!G4)+'03_Drivers'!G5 -> 203875.88 | H4: =(G4-'03_Drivers'!G5)*(1+'03_Drivers'!H4)+'03_Drivers'!H5 -> 209992.16 | I4: =(H4-'03_Drivers'!H5)*(1+'03_Drivers'!I4)+'03_Drivers'!I5 -> 216291.92
D5: Retail, Merchandising & Licensing | E5: ='02_Historical'!D3*(1+'03_Drivers'!E6) -> 152117.7 | F5: =E5*(1+'03_Drivers'!F6) -> 159723.58 | G5: =F5*(1+'03_Drivers'!G6) -> 167709.76 | H5: =G5*(1+'03_Drivers'!H6) -> 176095.25 | I5: =H5*(1+'03_Drivers'!I6) -> 184900.02
D6: Total Commercial Revenue | E6: =E4 + E5 -> 335227.7 | F6: =F4 + F5 -> 347661.34 | G6: =G4 + G5 -> 371585.65 | H6: =H4 + H5 -> 386087.41 | I6: =I4 + I5 -> 401191.94
D7: Broadcasting Revenue | E7: ='03_Drivers'!E7 -> 145000 | F7: ='03_Drivers'!F7 -> 185000 | G7: ='03_Drivers'!G7 -> 230000 | H7: ='03_Drivers'!H7 -> 235000 | I7: ='03_Drivers'!I7 -> 240000
D8: Matchday Revenue | E8: ='03_Drivers'!E8 -> 135000 | F8: ='03_Drivers'!F8 -> 150000 | G8: ='03_Drivers'!G8 -> 165000 | H8: ='03_Drivers'!H8 -> 170000 | I8: ='03_Drivers'!I8 -> 175000
D10: Total Revenue | E10: =sum(E6:E8) -> 615227.7 | F10: =sum(F6:F8) -> 682661.33 | G10: =sum(G6:G8) -> 766585.65 | H10: =sum(H6:H8) -> 791087.41 | I10: =sum(I6:I8) -> 816191.94
D12: Employee Benefit Expenses | E12: =-E10 * '03_Drivers'!E9 -> -307613.85 | F12: =-F10 * '03_Drivers'!F9 -> -327677.44 | G12: =-G10 * '03_Drivers'!G9 -> -360295.25 | H12: =-H10 * '03_Drivers'!H9 -> -363900.21 | I12: =-I10 * '03_Drivers'!I9 -> -367286.37
D13: Other Operating Expenses | E13: =-E10 * '03_Drivers'!E10 -> -146424.19 | F13: =-F10 * '03_Drivers'!F10 -> -165886.7 | G13: =-G10 * '03_Drivers'!G10 -> -186280.31 | H13: =-H10 * '03_Drivers'!H10 -> -189860.98 | I13: =-I10 * '03_Drivers'!I10 -> -194253.68
D14: Depreciation & Impairment | E14: ='03_Drivers'!E11 -> -16000 | F14: ='03_Drivers'!F11 -> -16500 | G14: ='03_Drivers'!G11 -> -17000 | H14: ='03_Drivers'!H11 -> -17500 | I14: ='03_Drivers'!I11 -> -18000
D15: Amortisation (Player Registrations) | E15: ='03_Drivers'!E12 -> -170000 | F15: ='03_Drivers'!F12 -> -175000 | G15: ='03_Drivers'!G12 -> -180000 | H15: ='03_Drivers'!H12 -> -185000 | I15: ='03_Drivers'!I12 -> -190000
D17: Operating Profit / (Loss) [EBIT] | E17: =SUM(E10, E12:E15) -> -24810.343 | F17: =SUM(F10, F12:F15) -> -2402.8102 | G17: =SUM(G10, G12:G15) -> 23010.081 | H17: =SUM(H10, H12:H15) -> 34826.223 | I17: =SUM(I10, I12:I15) -> 46651.885
D19: Taxes on EBIT (25%) | E19: =IF(E17>0, -E17 * 0.25, 0) -> 0 | F19: =IF(F17>0, -F17 * 0.25, 0) -> 0 | G19: =IF(G17>0, -G17 * 0.25, 0) -> -5752.5202 | H19: =IF(H17>0, -H17 * 0.25, 0) -> -8706.5559 | I19: =IF(I17>0, -I17 * 0.25, 0) -> -11662.971
D20: NOPAT | E20: =E17 + E19 -> -24810.343 | F20: =F17 + F19 -> -2402.8102 | G20: =G17 + G19 -> 17257.56 | H20: =H17 + H19 -> 26119.668 | I20: =I17 + I19 -> 34988.914
D22: Plus: D&A (Addback) | E22: =-(E14 + E15) -> 186000 | F22: =-(F14 + F15) -> 191500 | G22: =-(G14 + G15) -> 197000 | H22: =-(H14 + H15) -> 202500 | I22: =-(I14 + I15) -> 208000
D23: Less: Tangible PPE & CapEx | E23: ='03_Drivers'!E14 -> -20000 | F23: ='03_Drivers'!F14 -> -20000 | G23: ='03_Drivers'!G14 -> -20000 | H23: ='03_Drivers'!H14 -> -20000 | I23: ='03_Drivers'!I14 -> -20000
D24: Less: Net Player Intangible CapEx | E24: ='03_Drivers'!E13 -> -140000 | F24: ='03_Drivers'!F13 -> -140000 | G24: ='03_Drivers'!G13 -> -140000 | H24: ='03_Drivers'!H13 -> -140000 | I24: ='03_Drivers'!I13 -> -140000
D25: Less: Change in NWC | E25: ='03_Drivers'!E15 -> -5000 | F25: ='03_Drivers'!F15 -> -5000 | G25: ='03_Drivers'!G15 -> -5000 | H25: ='03_Drivers'!H15 -> -5000 | I25: ='03_Drivers'!I15 -> -5000
D26: Unlevered Free Cash Flow | E26: =SUM(E20, E22:E25) -> -3810.3426 | F26: =SUM(F20, F22:F25) -> 24097.19 | G26: =SUM(G20, G22:G25) -> 49257.56 | H26: =SUM(H20, H22:H25) -> 63619.668 | I26: =SUM(I20, I22:I25) -> 77988.914

Sheet 05_WACC
A2: Risk- Free Rate | B2: 0.0425
A3: Equity RIsk Premium | B3: 0.0525
A4: Peer Unlevered Beta | B4: 0.7
A5: Target Debt-to-Equity | B5: 0.15
A6: Marginal Tax Rate | B6: 0.25
A7: Re-levered Beta | B7: =B4 * (1 + (1 - B6) * B5) -> 0.77875
A8: Cost of Equity | B8: =B2 + (B7 * B3) -> 0.083384375
A10: Cost of Debt (Pre-Tax) | B10: 0.065
A11: Cost of Debt (After-Tax) | B11: =B10 * (1 - B6) -> 0.04875
A13: Weight of Equity | B13: =('06_Valuation'!B30 * '06_Valuation'!B26 / 1000 / '06_Valuation'!B28) / (('06_Valuation'!B30 * '06_Valuation'!B26 / 1000 / '06_Valuation'!B28) - '02_Historical'!D34) -> 0.81438243
A14: Weight of Debt | B14: =1-B13 -> 0.18561757
A16: Weighted Average Cost of Capital | B16: =(B8 * B13) + (B11 * B14) -> 0.076955626

Sheet 06_Valuation
B1: FY26E | C1: FY27E | D1: FY28E | E1: FY29E | F1: FY30E
A2: Unlevered Free Cash Flow | B2: ='04_DCF_Model'!E26 -> -3810.3426 | C2: ='04_DCF_Model'!F26 -> 24097.19 | D2: ='04_DCF_Model'!G26 -> 49257.56 | E2: ='04_DCF_Model'!H26 -> 63619.668 | F2: ='04_DCF_Model'!I26 -> 77988.914 | I2: 0.075 | J2: 0.08 | K2: 0.085 | L2: 0.09 | M2: 0.095
A3: Time Period | B3: 1 | C3: =B3+1 -> 2 | D3: =C3+1 -> 3 | E3: =D3+1 -> 4 | F3: =E3+1 -> 5 | H3: 0.015 | I3: =IF(OR(ISBLANK(I$2), I$2<=$H3), "-", (((SUMPRODUCT($B$2:$F$2,(1+I$2)^-($B$3:$F$3-0.5)) + ((($F$2 * (1 + $H3)) / (I$2 - $H3)) / ((1 + I$2)^(5 - 0.5))) + $B$19 + $B$20) * 1000 / $B$26) * $B$28)) -> 4.3111534 | J3: =IF(OR(ISBLANK(J$2), J$2<=$H3), "-", (((SUMPRODUCT($B$2:$F$2,(1+J$2)^-($B$3:$F$3-0.5)) + ((($F$2 * (1 + $H3)) / (J$2 - $H3)) / ((1 + J$2)^(5 - 0.5))) + $B$19 + $B$20) * 1000 / $B$26) * $B$28)) -> 3.6021429 | K3: =IF(OR(ISBLANK(K$2), K$2<=$H3), "-", (((SUMPRODUCT($B$2:$F$2,(1+K$2)^-($B$3:$F$3-0.5)) + ((($F$2 * (1 + $H3)) / (K$2 - $H3)) / ((1 + K$2)^(5 - 0.5))) + $B$19 + $B$20) * 1000 / $B$26) * $B$28)) -> 2.9952594 | L3: =IF(OR(ISBLANK(L$2), L$2<=$H3), "-", (((SUMPRODUCT($B$2:$F$2,(1+L$2)^-($B$3:$F$3-0.5)) + ((($F$2 * (1 + $H3)) / (L$2 - $H3)) / ((1 + L$2)^(5 - 0.5))) + $B$19 + $B$20) * 1000 / $B$26) * $B$28)) -> 2.470061 | M3: =IF(OR(ISBLANK(M$2), M$2<=$H3), "-", (((SUMPRODUCT($B$2:$F$2,(1+M$2)^-($B$3:$F$3-0.5)) + ((($F$2 * (1 + $H3)) / (M$2 - $H3)) / ((1 + M$2)^(5 - 0.5))) + $B$19 + $B$20) * 1000 / $B$26) * $B$28)) -> 2.0112167
A4: Mid-Year Discount Factor | B4: =1 / (1 + '05_WACC'!B16)^(B3 - 0.5) -> 0.96360955 | C4: =1 / (1 + '05_WACC'!B16)^(C3 - 0.5) -> 0.89475325 | D4: =1 / (1 + '05_WACC'!B16)^(D3 - 0.5) -> 0.83081719 | E4: =1 / (1 + '05_WACC'!B16)^(E3 - 0.5) -> 0.77144979 | F4: =1 / (1 + '05_WACC'!B16)^(F3 - 0.5) -> 0.71632459 | H4: 0.0175 | I4: =IF(OR(ISBLANK(I$2), I$2<=$H4), "-", (((SUMPRODUCT($B$2:$F$2,(1+I$2)^-($B$3:$F$3-0.5)) + ((($F$2 * (1 + $H4)) / (I$2 - $H4)) / ((1 + I$2)^(5 - 0.5))) + $B$19 + $B$20) * 1000 / $B$26) * $B$28)) -> 4.6419368 | J4: =IF(OR(ISBLANK(J$2), J$2<=$H4), "-", (((SUMPRODUCT($B$2:$F$2,(1+J$2)^-($B$3:$F$3-0.5)) + ((($F$2 * (1 + $H4)) / (J$2 - $H4)) / ((1 + J$2)^(5 - 0.5))) + $B$19 + $B$20) * 1000 / $B$26) * $B$28)) -> 3.8785288 | K4: =IF(OR(ISBLANK(K$2), K$2<=$H4), "-", (((SUMPRODUCT($B$2:$F$2,(1+K$2)^-($B$3:$F$3-0.5)) + ((($F$2 * (1 + $H4)) / (K$2 - $H4)) / ((1 + K$2)^(5 - 0.5))) + $B$19 + $B$20) * 1000 / $B$26) * $B$28)) -> 3.229082 | L4: =IF(OR(ISBLANK(L$2), L$2<=$H4), "-", (((SUMPRODUCT($B$2:$F$2,(1+L$2)^-($B$3:$F$3-0.5)) + ((($F$2 * (1 + $H4)) / (L$2 - $H4)) / ((1 + L$2)^(5 - 0.5))) + $B$19 + $B$20) * 1000 / $B$26) * $B$28)) -> 2.6700013 | M4: =IF(OR(ISBLANK(M$2), M$2<=$H4), "-", (((SUMPRODUCT($B$2:$F$2,(1+M$2)^-($B$3:$F$3-0.5)) + ((($F$2 * (1 + $H4)) / (M$2 - $H4)) / ((1 + M$2)^(5 - 0.5))) + $B$19 + $B$20) * 1000 / $B$26) * $B$28)) -> 2.1837812
A5: Present Value of UFCF | B5: =B2*B4 -> -3671.6825 | C5: =C2*C4 -> 21561.039 | D5: =D2*D4 -> 40924.028 | E5: =E2*E4 -> 49079.379 | F5: =F2*F4 -> 55865.376 | H5: 0.02 | I5: =IF(OR(ISBLANK(I$2), I$2<=$H5), "-", (((SUMPRODUCT($B$2:$F$2,(1+I$2)^-($B$3:$F$3-0.5)) + ((($F$2 * (1 + $H5)) / (I$2 - $H5)) / ((1 + I$2)^(5 - 0.5))) + $B$19 + $B$20) * 1000 / $B$26) * $B$28)) -> 5.0027914 | J5: =IF(OR(ISBLANK(J$2), J$2<=$H5), "-", (((SUMPRODUCT($B$2:$F$2,(1+J$2)^-($B$3:$F$3-0.5)) + ((($F$2 * (1 + $H5)) / (J$2 - $H5)) / ((1 + J$2)^(5 - 0.5))) + $B$19 + $B$20) * 1000 / $B$26) * $B$28)) -> 4.1779469 | K5: =IF(OR(ISBLANK(K$2), K$2<=$H5), "-", (((SUMPRODUCT($B$2:$F$2,(1+K$2)^-($B$3:$F$3-0.5)) + ((($F$2 * (1 + $H5)) / (K$2 - $H5)) / ((1 + K$2)^(5 - 0.5))) + $B$19 + $B$20) * 1000 / $B$26) * $B$28)) -> 3.480891 | L5: =IF(OR(ISBLANK(L$2), L$2<=$H5), "-", (((SUMPRODUCT($B$2:$F$2,(1+L$2)^-($B$3:$F$3-0.5)) + ((($F$2 * (1 + $H5)) / (L$2 - $H5)) / ((1 + L$2)^(5 - 0.5))) + $B$19 + $B$20) * 1000 / $B$26) * $B$28)) -> 2.8842231 | M5: =IF(OR(ISBLANK(M$2), M$2<=$H5), "-", (((SUMPRODUCT($B$2:$F$2,(1+M$2)^-($B$3:$F$3-0.5)) + ((($F$2 * (1 + $H5)) / (M$2 - $H5)) / ((1 + M$2)^(5 - 0.5))) + $B$19 + $B$20) * 1000 / $B$26) * $B$28)) -> 2.3678499
H6: 0.0225 | I6: =IF(OR(ISBLANK(I$2), I$2<=$H6), "-", (((SUMPRODUCT($B$2:$F$2,(1+I$2)^-($B$3:$F$3-0.5)) + ((($F$2 * (1 + $H6)) / (I$2 - $H6)) / ((1 + I$2)^(5 - 0.5))) + $B$19 + $B$20) * 1000 / $B$26) * $B$28)) -> 5.3980132 | J6: =IF(OR(ISBLANK(J$2), J$2<=$H6), "-", (((SUMPRODUCT($B$2:$F$2,(1+J$2)^-($B$3:$F$3-0.5)) + ((($F$2 * (1 + $H6)) / (J$2 - $H6)) / ((1 + J$2)^(5 - 0.5))) + $B$19 + $B$20) * 1000 / $B$26) * $B$28)) -> 4.5034014 | K6: =IF(OR(ISBLANK(K$2), K$2<=$H6), "-", (((SUMPRODUCT($B$2:$F$2,(1+K$2)^-($B$3:$F$3-0.5)) + ((($F$2 * (1 + $H6)) / (K$2 - $H6)) / ((1 + K$2)^(5 - 0.5))) + $B$19 + $B$20) * 1000 / $B$26) * $B$28)) -> 3.7528447 | L6: =IF(OR(ISBLANK(L$2), L$2<=$H6), "-", (((SUMPRODUCT($B$2:$F$2,(1+L$2)^-($B$3:$F$3-0.5)) + ((($F$2 * (1 + $H6)) / (L$2 - $H6)) / ((1 + L$2)^(5 - 0.5))) + $B$19 + $B$20) * 1000 / $B$26) * $B$28)) -> 3.1143132 | M6: =IF(OR(ISBLANK(M$2), M$2<=$H6), "-", (((SUMPRODUCT($B$2:$F$2,(1+M$2)^-($B$3:$F$3-0.5)) + ((($F$2 * (1 + $H6)) / (M$2 - $H6)) / ((1 + M$2)^(5 - 0.5))) + $B$19 + $B$20) * 1000 / $B$26) * $B$28)) -> 2.5646131
A7: Cumulative PV of UFCFs | B7: =SUM(B5:F5) -> 163758.14 | H7: 0.025 | I7: =IF(OR(ISBLANK(I$2), I$2<=$H7), "-", (((SUMPRODUCT($B$2:$F$2,(1+I$2)^-($B$3:$F$3-0.5)) + ((($F$2 * (1 + $H7)) / (I$2 - $H7)) / ((1 + I$2)^(5 - 0.5))) + $B$19 + $B$20) * 1000 / $B$26) * $B$28)) -> 5.8327571 | J7: =IF(OR(ISBLANK(J$2), J$2<=$H7), "-", (((SUMPRODUCT($B$2:$F$2,(1+J$2)^-($B$3:$F$3-0.5)) + ((($F$2 * (1 + $H7)) / (J$2 - $H7)) / ((1 + J$2)^(5 - 0.5))) + $B$19 + $B$20) * 1000 / $B$26) * $B$28)) -> 4.8584426 | K7: =IF(OR(ISBLANK(K$2), K$2<=$H7), "-", (((SUMPRODUCT($B$2:$F$2,(1+K$2)^-($B$3:$F$3-0.5)) + ((($F$2 * (1 + $H7)) / (K$2 - $H7)) / ((1 + K$2)^(5 - 0.5))) + $B$19 + $B$20) * 1000 / $B$26) * $B$28)) -> 4.0474612 | L7: =IF(OR(ISBLANK(L$2), L$2<=$H7), "-", (((SUMPRODUCT($B$2:$F$2,(1+L$2)^-($B$3:$F$3-0.5)) + ((($F$2 * (1 + $H7)) / (L$2 - $H7)) / ((1 + L$2)^(5 - 0.5))) + $B$19 + $B$20) * 1000 / $B$26) * $B$28)) -> 3.3621025 | M7: =IF(OR(ISBLANK(M$2), M$2<=$H7), "-", (((SUMPRODUCT($B$2:$F$2,(1+M$2)^-($B$3:$F$3-0.5)) + ((($F$2 * (1 + $H7)) / (M$2 - $H7)) / ((1 + M$2)^(5 - 0.5))) + $B$19 + $B$20) * 1000 / $B$26) * $B$28)) -> 2.7754307
A9: Perpetuity Growth Rate | B9: 0.02
A10: Terminal Year Normalised UFCF | B10: =F2 * (1 + B9) -> 79548.692 | I10: 0.075 | J10: 0.08 | K10: 0.085 | L10: 0.09 | M10: 0.095
A11: TV (Gordon Growth) | B11: =B10 / ('05_WACC'!B16 - B9) -> 1396678.4 | H11: 10 | I11: =(((SUMPRODUCT($B$2:$F$2,(1+I$10)^-($B$3:$F$3-0.5)) + ((('04_DCF_Model'!$I$17 - '04_DCF_Model'!$I$14 - '04_DCF_Model'!$I$15) * $H11) * (1 / (1 + I$10)^(5 - 0.5)))) + $B$19 + $B$20) * 1000 / $B$26) * $B$28 -> 10.99304 | J11: =(((SUMPRODUCT($B$2:$F$2,(1+J$10)^-($B$3:$F$3-0.5)) + ((('04_DCF_Model'!$I$17 - '04_DCF_Model'!$I$14 - '04_DCF_Model'!$I$15) * $H11) * (1 / (1 + J$10)^(5 - 0.5)))) + $B$19 + $B$20) * 1000 / $B$26) * $B$28 -> 10.687096 | K11: =(((SUMPRODUCT($B$2:$F$2,(1+K$10)^-($B$3:$F$3-0.5)) + ((('04_DCF_Model'!$I$17 - '04_DCF_Model'!$I$14 - '04_DCF_Model'!$I$15) * $H11) * (1 / (1 + K$10)^(5 - 0.5)))) + $B$19 + $B$20) * 1000 / $B$26) * $B$28 -> 10.38877 | L11: =(((SUMPRODUCT($B$2:$F$2,(1+L$10)^-($B$3:$F$3-0.5)) + ((('04_DCF_Model'!$I$17 - '04_DCF_Model'!$I$14 - '04_DCF_Model'!$I$15) * $H11) * (1 / (1 + L$10)^(5 - 0.5)))) + $B$19 + $B$20) * 1000 / $B$26) * $B$28 -> 10.097839 | M11: =(((SUMPRODUCT($B$2:$F$2,(1+M$10)^-($B$3:$F$3-0.5)) + ((('04_DCF_Model'!$I$17 - '04_DCF_Model'!$I$14 - '04_DCF_Model'!$I$15) * $H11) * (1 / (1 + M$10)^(5 - 0.5)))) + $B$19 + $B$20) * 1000 / $B$26) * $B$28 -> 9.8140846
A12: PV OF TV (Gordon Growth) | B12: =B11 * F4 -> 1000475.1 | H12: 11 | I12: =(((SUMPRODUCT($B$2:$F$2,(1+I$10)^-($B$3:$F$3-0.5)) + ((('04_DCF_Model'!$I$17 - '04_DCF_Model'!$I$14 - '04_DCF_Model'!$I$15) * $H12) * (1 / (1 + I$10)^(5 - 0.5)))) + $B$19 + $B$20) * 1000 / $B$26) * $B$28 -> 12.379567 | J12: =(((SUMPRODUCT($B$2:$F$2,(1+J$10)^-($B$3:$F$3-0.5)) + ((('04_DCF_Model'!$I$17 - '04_DCF_Model'!$I$14 - '04_DCF_Model'!$I$15) * $H12) * (1 / (1 + J$10)^(5 - 0.5)))) + $B$19 + $B$20) * 1000 / $B$26) * $B$28 -> 12.04497 | K12: =(((SUMPRODUCT($B$2:$F$2,(1+K$10)^-($B$3:$F$3-0.5)) + ((('04_DCF_Model'!$I$17 - '04_DCF_Model'!$I$14 - '04_DCF_Model'!$I$15) * $H12) * (1 / (1 + K$10)^(5 - 0.5)))) + $B$19 + $B$20) * 1000 / $B$26) * $B$28 -> 11.718712 | L12: =(((SUMPRODUCT($B$2:$F$2,(1+L$10)^-($B$3:$F$3-0.5)) + ((('04_DCF_Model'!$I$17 - '04_DCF_Model'!$I$14 - '04_DCF_Model'!$I$15) * $H12) * (1 / (1 + L$10)^(5 - 0.5)))) + $B$19 + $B$20) * 1000 / $B$26) * $B$28 -> 11.400547 | M12: =(((SUMPRODUCT($B$2:$F$2,(1+M$10)^-($B$3:$F$3-0.5)) + ((('04_DCF_Model'!$I$17 - '04_DCF_Model'!$I$14 - '04_DCF_Model'!$I$15) * $H12) * (1 / (1 + M$10)^(5 - 0.5)))) + $B$19 + $B$20) * 1000 / $B$26) * $B$28 -> 11.090238
H13: 12 | I13: =(((SUMPRODUCT($B$2:$F$2,(1+I$10)^-($B$3:$F$3-0.5)) + ((('04_DCF_Model'!$I$17 - '04_DCF_Model'!$I$14 - '04_DCF_Model'!$I$15) * $H13) * (1 / (1 + I$10)^(5 - 0.5)))) + $B$19 + $B$20) * 1000 / $B$26) * $B$28 -> 13.766094 | J13: =(((SUMPRODUCT($B$2:$F$2,(1+J$10)^-($B$3:$F$3-0.5)) + ((('04_DCF_Model'!$I$17 - '04_DCF_Model'!$I$14 - '04_DCF_Model'!$I$15) * $H13) * (1 / (1 + J$10)^(5 - 0.5)))) + $B$19 + $B$20) * 1000 / $B$26) * $B$28 -> 13.402844 | K13: =(((SUMPRODUCT($B$2:$F$2,(1+K$10)^-($B$3:$F$3-0.5)) + ((('04_DCF_Model'!$I$17 - '04_DCF_Model'!$I$14 - '04_DCF_Model'!$I$15) * $H13) * (1 / (1 + K$10)^(5 - 0.5)))) + $B$19 + $B$20) * 1000 / $B$26) * $B$28 -> 13.048654 | L13: =(((SUMPRODUCT($B$2:$F$2,(1+L$10)^-($B$3:$F$3-0.5)) + ((('04_DCF_Model'!$I$17 - '04_DCF_Model'!$I$14 - '04_DCF_Model'!$I$15) * $H13) * (1 / (1 + L$10)^(5 - 0.5)))) + $B$19 + $B$20) * 1000 / $B$26) * $B$28 -> 12.703255 | M13: =(((SUMPRODUCT($B$2:$F$2,(1+M$10)^-($B$3:$F$3-0.5)) + ((('04_DCF_Model'!$I$17 - '04_DCF_Model'!$I$14 - '04_DCF_Model'!$I$15) * $H13) * (1 / (1 + M$10)^(5 - 0.5)))) + $B$19 + $B$20) * 1000 / $B$26) * $B$28 -> 12.366392
A14: Exit Multiple (EV / EBITDA) | B14: 12.5 | H14: 13 | I14: =(((SUMPRODUCT($B$2:$F$2,(1+I$10)^-($B$3:$F$3-0.5)) + ((('04_DCF_Model'!$I$17 - '04_DCF_Model'!$I$14 - '04_DCF_Model'!$I$15) * $H14) * (1 / (1 + I$10)^(5 - 0.5)))) + $B$19 + $B$20) * 1000 / $B$26) * $B$28 -> 15.152621 | J14: =(((SUMPRODUCT($B$2:$F$2,(1+J$10)^-($B$3:$F$3-0.5)) + ((('04_DCF_Model'!$I$17 - '04_DCF_Model'!$I$14 - '04_DCF_Model'!$I$15) * $H14) * (1 / (1 + J$10)^(5 - 0.5)))) + $B$19 + $B$20) * 1000 / $B$26) * $B$28 -> 14.760718 | K14: =(((SUMPRODUCT($B$2:$F$2,(1+K$10)^-($B$3:$F$3-0.5)) + ((('04_DCF_Model'!$I$17 - '04_DCF_Model'!$I$14 - '04_DCF_Model'!$I$15) * $H14) * (1 / (1 + K$10)^(5 - 0.5)))) + $B$19 + $B$20) * 1000 / $B$26) * $B$28 -> 14.378595 | L14: =(((SUMPRODUCT($B$2:$F$2,(1+L$10)^-($B$3:$F$3-0.5)) + ((('04_DCF_Model'!$I$17 - '04_DCF_Model'!$I$14 - '04_DCF_Model'!$I$15) * $H14) * (1 / (1 + L$10)^(5 - 0.5)))) + $B$19 + $B$20) * 1000 / $B$26) * $B$28 -> 14.005964 | M14: =(((SUMPRODUCT($B$2:$F$2,(1+M$10)^-($B$3:$F$3-0.5)) + ((('04_DCF_Model'!$I$17 - '04_DCF_Model'!$I$14 - '04_DCF_Model'!$I$15) * $H14) * (1 / (1 + M$10)^(5 - 0.5)))) + $B$19 + $B$20) * 1000 / $B$26) * $B$28 -> 13.642545
A15: TV (Exit Multiple) | B15: =('04_DCF_Model'!I17 - '04_DCF_Model'!I14 - '04_DCF_Model'!I15) * B14 -> 3183148.6 | H15: 14 | I15: =(((SUMPRODUCT($B$2:$F$2,(1+I$10)^-($B$3:$F$3-0.5)) + ((('04_DCF_Model'!$I$17 - '04_DCF_Model'!$I$14 - '04_DCF_Model'!$I$15) * $H15) * (1 / (1 + I$10)^(5 - 0.5)))) + $B$19 + $B$20) * 1000 / $B$26) * $B$28 -> 16.539148 | J15: =(((SUMPRODUCT($B$2:$F$2,(1+J$10)^-($B$3:$F$3-0.5)) + ((('04_DCF_Model'!$I$17 - '04_DCF_Model'!$I$14 - '04_DCF_Model'!$I$15) * $H15) * (1 / (1 + J$10)^(5 - 0.5)))) + $B$19 + $B$20) * 1000 / $B$26) * $B$28 -> 16.118593 | K15: =(((SUMPRODUCT($B$2:$F$2,(1+K$10)^-($B$3:$F$3-0.5)) + ((('04_DCF_Model'!$I$17 - '04_DCF_Model'!$I$14 - '04_DCF_Model'!$I$15) * $H15) * (1 / (1 + K$10)^(5 - 0.5)))) + $B$19 + $B$20) * 1000 / $B$26) * $B$28 -> 15.708537 | L15: =(((SUMPRODUCT($B$2:$F$2,(1+L$10)^-($B$3:$F$3-0.5)) + ((('04_DCF_Model'!$I$17 - '04_DCF_Model'!$I$14 - '04_DCF_Model'!$I$15) * $H15) * (1 / (1 + L$10)^(5 - 0.5)))) + $B$19 + $B$20) * 1000 / $B$26) * $B$28 -> 15.308672 | M15: =(((SUMPRODUCT($B$2:$F$2,(1+M$10)^-($B$3:$F$3-0.5)) + ((('04_DCF_Model'!$I$17 - '04_DCF_Model'!$I$14 - '04_DCF_Model'!$I$15) * $H15) * (1 / (1 + M$10)^(5 - 0.5)))) + $B$19 + $B$20) * 1000 / $B$26) * $B$28 -> 14.918698
A16: PV of TV (Exit Multiple) | B16: =B15 * F4 -> 2280167.6
A18: Enterprise Value (EV) | B18: =B7 + B16 -> 2443925.7
A19: Less: Total Gross Debt | B19: ='02_Historical'!D34 -> -631855
A20: Plus: Cash & Cash Equivalents | B20: ='02_Historical'!D30 -> 86105
A21: Implied Equity Value (£'000s) | B21: =B18 + B19 + B20 -> 1898175.7
A23: Class A Shares Outstanding | B23: 57769080
A24: Less: Treasury Shares | B24: -1682896
A25: Class B Shares Outstanding | B25: 116348173
A26: Total Diluted Shares | B26: =SUM(B23:B25) -> 172434357
A27: Implied Share Price (GBP) | B27: =(B21 * 1000) / B26 -> 11.008106
A28: Exchange Rate (USD / GBP) | B28: 1.3
A29: Implied Share Price (USD) | B29: =B27*B28 -> 14.310538
A30: Current Share Price (USD) | B30: 20.9
A31: Implied Upside / (Downside) | B31: =(B29 / B30) - 1 -> -0.31528526

Sheet 07_Summary
A1: Exchange / Ticker | B1: NYSE / MANU
A2: Rating | B2: Underweight / Hold
A3: Current Share Price | B3: ='06_Valuation'!B30 -> 20.9
A4: 12-Month Target Price | B4: ='06_Valuation'!B29 -> 14.310538
A5: Implied Return | B5: =(B4 / B3) - 1 -> -0.31528526
A8: Valuation Methodology | B8: Min Price ($) | C8: Target / Midpoint ($) | D8: Max Price ($) | E8: Implied Upside / (Downside) %
A9: 52-Week Trading Range | B9: 14.2 | D9: 22.5
A10: DCF Intrinsic Floor (Gordon Growth) | B10: ='06_Valuation'!M3 -> 2.0112167 | C10: ='06_Valuation'!J5 -> 4.1779469 | D10: ='06_Valuation'!I7 -> 5.8327571 | E10: =(C10 / $B$3) - 1 -> -0.80009823
A11: DCF Operating Base Case (Exit Multiple) | B11: ='06_Valuation'!M11 -> 9.8140846 | C11: ='06_Valuation'!B29 -> 14.310538 | D11: ='06_Valuation'!I15 -> 16.539148 | E11: ='06_Valuation'!B31 -> -0.31528526
A12: Public Trading Comparables (EV/EBITDA) | C12: =((('02_Historical'!B42 * 3.98) - '06_Valuation'!B19 + '06_Valuation'!B20) * 1000 / '06_Valuation'!B26) * '06_Valuation'!B28 -> 10.008044 | E12: =(C12 / $B$3) - 1 -> -0.52114624
A13: Public Trading Comparables (EV/Sales) | C13: =((('02_Historical'!D7 * 1.13) - '06_Valuation'!B19 + '06_Valuation'!B20) * 1000 / '06_Valuation'!B26) * '06_Valuation'!B28 -> 11.090928 | E13: =(C13 / $B$3) - 1 -> -0.46933358
A14: Precedent Transaction (INEOS Deal) | C14: 33 | E14: =(C14 / $B$3) - 1 -> 0.57894737
A15: Current Market Price Reference | C15: ='06_Valuation'!B30 -> 20.9 | E15: 0
A17: Operational Reality vs. Multiple Expansion: Manchester United's fundamental cash generation remains highly constrained by the capital intensity required to compete at the highest level of European football. While INEOS-led initiatives to rationalise the wage bill (targeting 45.0% of revenue by FY30E) and protections embedded in the Adidas extension provide a path for Adjusted EBITDA to expand toward £255M, free cash flow conversion is dampened by recurring player amortisation (£190M run-rate) and substantial net transfer CapEx (£140M p.a.). The pure operating yield of the club simply does not support current market valuations.
A22: The Public vs. Private Disconnect: A fundamental Unlevered DCF yields a base case of $4.18 per share (Gordon Growth) and $14. per share (12.5x Exit Multiple). Yet, the stock trades at $20.90, supported by the precedent $33.00 per share paid by Sir Jim Ratcliffe / INEOS for a 28.9% stake. This massive divergence highlights the "trophy asset" premium and global scarcity value assigned to premier sports franchises in private markets, completely decoupling the stock's trading level from traditional institutional cash-flow metrics. The stock currently behaves more as a proxy for future control-premium buyouts than a yield-generating equity.
A27: Key Catalysts & Downside Risks: Near-term cash flow is heavily tethered to European qualification. Returning to the UEFA Champions League under the expanded 36-team Swiss model by FY28E is critical to lifting broadcasting revenues beyond £230M and avoiding ongoing £10M penalty deductions on the Adidas contract. Furthermore, a major downside risk to free cash flow remains the Old Trafford stadium infrastructure. Our model assumes baseline maintenance CapEx (£20M p.a.), but any full-scale stadium redevelopment or new build—absent external localized financing or municipal partnerships—would require hundreds of millions in fresh debt or equity, severely diluting future shareholder value.
